jupyter_instructortools/__init__.py
jupyter_instructortools-0.8.0.data/data/share/jupyter/labextensions/jupyter-instructortools/package.json
jupyter_instructortools-0.8.0.data/data/share/jupyter/labextensions/jupyter-instructortools/static/509.2c605a792a8760908c87.js
jupyter_instructortools-0.8.0.data/data/share/jupyter/labextensions/jupyter-instructortools/static/728.05a0208492ab713ca9d1.js
jupyter_instructortools-0.8.0.data/data/share/jupyter/labextensions/jupyter-instructortools/static/remoteEntry.6d32668e0a41d0b87d91.js
jupyter_instructortools-0.8.0.data/data/share/jupyter/labextensions/jupyter-instructortools/static/style.js
jupyter_instructortools-0.8.0.data/data/share/jupyter/labextensions/jupyter-instructortools/static/third-party-licenses.json
jupyter_instructortools-0.8.0.data/data/share/jupyter/labextensions/jupyter-instructortools/install.json
jupyter_instructortools-0.8.0.dist-info/METADATA
jupyter_instructortools-0.8.0.dist-info/WHEEL
jupyter_instructortools-0.8.0.dist-info/licenses/LICENSE
jupyter_instructortools-0.8.0.dist-info/RECORD
