Metadata-Version: 2.3
Name: jupyter-instructortools
Version: 0.8.0
Dynamic: Keywords
Summary: Tool to assist instructors in creating notebook templates for student Jupyter worksheets.
Project-URL: Homepage, https://github.com/JupyterPhysSciLab/jupyter-instructortools
Project-URL: Bug Tracker, https://github.com/JupyterPhysSciLab/jupyter-instructortools/issues
Project-URL: Repository, https://github.com/JupyterPhysSciLab/jupyter-instructortools.git
Author-email: Jonathan Gutow <gutow@uwosh.edu>
License: BSD 3-Clause License
License-File: LICENSE
Classifier: Framework :: Jupyter
Classifier: Framework :: Jupyter :: JupyterLab
Classifier: Framework :: Jupyter :: JupyterLab :: 4
Classifier: Framework :: Jupyter :: JupyterLab :: Extensions
Classifier: Framework :: Jupyter :: JupyterLab :: Extensions :: Prebuilt
Classifier: License :: OSI Approved :: BSD License
Classifier: Programming Language :: Python
Classifier: Programming Language :: Python :: 3
Classifier: Programming Language :: Python :: 3.8
Classifier: Programming Language :: Python :: 3.9
Classifier: Programming Language :: Python :: 3.10
Classifier: Programming Language :: Python :: 3.11
Classifier: Programming Language :: Python :: 3.12
Requires-Python: >=3.8
Requires-Dist: jupyter-datainputtable>=0.8.0
Requires-Dist: jupyterlab<5,>=4.0.0
